README.rst
setup.cfg
setup.py
UCToolkit/UCToolkit.py
UCToolkit/__init__.py
UCToolkit/CUCM/schema/10.0/AXLAPI.wsdl
UCToolkit/CUCM/schema/10.0/AXLEnums.xsd
UCToolkit/CUCM/schema/10.0/AXLSoap.xsd
UCToolkit/CUCM/schema/10.5/AXLAPI.wsdl
UCToolkit/CUCM/schema/10.5/AXLEnums.xsd
UCToolkit/CUCM/schema/10.5/AXLSoap.xsd
UCToolkit/CUCM/schema/11.0/AXLAPI.wsdl
UCToolkit/CUCM/schema/11.0/AXLEnums.xsd
UCToolkit/CUCM/schema/11.0/AXLSoap.xsd
UCToolkit/CUCM/schema/11.5/AXLAPI.wsdl
UCToolkit/CUCM/schema/11.5/AXLEnums.xsd
UCToolkit/CUCM/schema/11.5/AXLSoap.xsd
UCToolkit/CUCM/schema/12.0/AXLAPI.wsdl
UCToolkit/CUCM/schema/12.0/AXLEnums.xsd
UCToolkit/CUCM/schema/12.0/AXLSoap.xsd
UCToolkit/CUCM/schema/12.5/AXLAPI.wsdl
UCToolkit/CUCM/schema/12.5/AXLEnums.xsd
UCToolkit/CUCM/schema/12.5/AXLSoap.xsd
UCToolkit/CUCM/schema/8.0/AXLAPI.wsdl
UCToolkit/CUCM/schema/8.0/AXLEnums.xsd
UCToolkit/CUCM/schema/8.0/AXLSoap.xsd
UCToolkit/CUCM/schema/8.5/AXLAPI.wsdl
UCToolkit/CUCM/schema/8.5/AXLEnums.xsd
UCToolkit/CUCM/schema/8.5/AXLSoap.xsd
UCToolkit/CUCM/schema/9.0/AXLAPI.wsdl
UCToolkit/CUCM/schema/9.0/AXLEnums.xsd
UCToolkit/CUCM/schema/9.0/AXLSoap.xsd
UCToolkit/CUCM/schema/9.1/AXLAPI.wsdl
UCToolkit/CUCM/schema/9.1/AXLEnums.xsd
UCToolkit/CUCM/schema/9.1/AXLSoap.xsd
UCToolkit/CUCM/schema/current/AXLAPI.wsdl
UCToolkit/CUCM/schema/current/AXLEnums.xsd
UCToolkit/CUCM/schema/current/AXLSoap.xsd
UCToolkit/IMP/schema/11.5/AXLAPI.wsdl
UCToolkit/IMP/schema/11.5/AXLEnums.xsd
UCToolkit/IMP/schema/11.5/AXLSoap.xsd
UCToolkit/IMP/schema/12.5/AXLAPI.wsdl
UCToolkit/IMP/schema/12.5/AXLEnums.xsd
UCToolkit/IMP/schema/12.5/AXLSoap.xsd
UCToolkit/paws/hardware_information_service.wsdl
ciscouctoolkit.egg-info/PKG-INFO
ciscouctoolkit.egg-info/SOURCES.txt
ciscouctoolkit.egg-info/dependency_links.txt
ciscouctoolkit.egg-info/requires.txt
ciscouctoolkit.egg-info/top_level.txt