Metadata-Version: 1.1
Name: ciscouctoolkit
Version: 1.412
Summary: Cisco CUCM AXL Library, PAWS, DIME, IMP AXL, Log Collection.
Home-page: https://github.com/MichaelRalston98/ciscouctoolkit
Author: Michael Ralston
Author-email: michaelaaralston2@gmail.com
License: MIT
Keywords: Cisco,Call Manager,CUCM,AXL,VoIP
Platform: UNKNOWN
Classifier: Programming Language :: Python :: 3
Classifier: License :: OSI Approved :: MIT License
Classifier: Operating System :: OS Independent
